varnamala.py
varnamala-0.0.1.dist-info/licenses/LICENSE
varnamala-0.0.1.dist-info/WHEEL
varnamala-0.0.1.dist-info/METADATA
varnamala-0.0.1.dist-info/RECORD
