Metadata-Version: 2.4
Name: varnamala
Version: 0.0.1
Summary: A simple package to provide readily usable varnamala
Author-email: Chaitanya Lakkundi <chaitanya.lakkundi@gmail.com>
License-Expression: MIT
License-File: LICENSE
